{
    "button": {
        "$type": "color",
        "primary": {
            "$value": "#fc0"
        },
        "primary-hover": {
            "$value": "#DAB21C"
        },
        "secondary": {
            "$value": "#FFFFFF"
        },
        "secondary-hover": {
            "$value": "#E8EEF6"
        },
        "tertiary": {
            "$value": "#FFFFFF00"
        },
        "tertiary-hover": {
            "$value": "#D2E4F5"
        },
        "cta": {
            "$value": "{button-primary}"
        },
        "cta-hover": {
            "$value": "{button-primary-hover}"
        }
    },
    "text": {
        "primary": {
            "$type": "color",
            "$value": "#002147"
        },
        "secondary": {
            "$type": "color",
            "$value": "#fff"
        },
        "tertiary": {
            "$type": "color",
            "$value": "{text-primary}"
        }
    },
    "general": {
        "color-1": {
            "$type": "color",
            "$value": "#011F42"
        },
        "color-2": {
            "$type": "color",
            "$value": "#00397A"
        },
        "color-3": {
            "$type": "color",
            "$value": "#E8F4FE"
        },
        "color-4": {
            "$type": "color",
            "$value": "{button-primary}"
        },
        "color-5": {
            "$type": "color",
            "$value": "#002D62"
        },
        "color-6": {
            "$type": "color",
            "$value": "#0057A8"
        }
    },
    "page": {
        "background-primary": {
            "$type": "color",
            "$value": "#FFFFFF"
        }
    },
    "container": {
        "$type": "dimension",
        "xsmall": {
            "$value": "12px"
        },
        "small": {
            "$value": "24px"
        },
        "medium": {
            "$value": "48px"
        },
        "large": {
            "$value": "96px"
        },
        "xlarge": {
            "$value": "120px"
        },
        "xxlarge": {
            "$value": "192px"
        }
    },
    "table": {
        "$type": "dimension",
        "small": {
            "$value": "4px 8px"
        },
        "medium": {
            "$value": "12px 16px"
        },
        "large": {
            "$value": "16px 24px"
        }
    },
    "badge": {
        "$type": "dimension",
        "small": {
            "$value": "2px 6px"
        },
        "large": {
            "$value": "4px 8px"
        }
    },
    "button-small": {
        "$type": "dimension",
        "$value": "8px 24px"
    },
    "button-medium": {
        "$type": "dimension",
        "$value": "12px 32px"
    },
    "button-large": {
        "$type": "dimension",
        "$value": "18px 40px"
    },
    "spacer": {
        "$type": "dimension",
        "extra-small": {
            "$value": "10px"
        },
        "small": {
            "$value": "20px"
        },
        "medium": {
            "$value": "40px"
        },
        "large": {
            "$value": "80px"
        }
    },
    "border": {
        "$type": "border",
        "primary": {
            "$value": {
                "radius": "4px",
                "width": "2px",
                "color": "#FFFFFF00",
                "style": "solid"
            }
        },
        "secondary": {
            "$value": {
                "radius": "4px",
                "width": "2px",
                "color": "#0057a8",
                "style": "solid"
            }
        },
        "footer": {
            "$value": {
                "radius": "0px",
                "width": "1px 0px 0px 0px",
                "color": "#99C6FF",
                "style": "solid"
            }
        },
        "image-radius-small": {
            "$value": {
                "radius": "12px",
                "width": "0px",
                "color": "#000000",
                "style": "solid"
            }
        },
        "card": {
            "$value": {
                "radius": "8px",
                "width": "2px",
                "color": "#00000000",
                "style": "solid"
            }
        }
    }
}